mcp_nvidia/__init__.py
mcp_nvidia/__main__.py
mcp_nvidia/http_server.py
mcp_nvidia/server.py
mcp_nvidia/lib/__init__.py
mcp_nvidia/lib/constants.py
mcp_nvidia/lib/content_discovery.py
mcp_nvidia/lib/deduplication.py
mcp_nvidia/lib/relevance.py
mcp_nvidia/lib/response_builders.py
mcp_nvidia/lib/search.py
mcp_nvidia/lib/snippet.py
mcp_nvidia/lib/utils.py
mcp_nvidia/sdk_generator/__init__.py
mcp_nvidia/sdk_generator/python_generator.py
mcp_nvidia/sdk_generator/typescript_generator.py
mcp_nvidia/ui/__init__.py
mcp_nvidia/ui/components.py
mcp_nvidia/ui/renderer.py
mcp_nvidia/ui/styles.py
mcp_nvidia/ui/templates.py
mcp_nvidia-0.5.0.dist-info/METADATA
mcp_nvidia-0.5.0.dist-info/WHEEL
mcp_nvidia-0.5.0.dist-info/entry_points.txt
mcp_nvidia-0.5.0.dist-info/licenses/LICENSE
mcp_nvidia-0.5.0.dist-info/RECORD
