Metadata-Version: 2.4
Name: mcp-nvidia
Version: 0.5.0
Summary: MCP server to search across NVIDIA blogs and releases to empower LLMs to better answer NVIDIA specific queries
Project-URL: Homepage, https://github.com/bharatr21/mcp-nvidia
Project-URL: Repository, https://github.com/bharatr21/mcp-nvidia.git
Project-URL: Issues, https://github.com/bharatr21/mcp-nvidia/issues
Project-URL: Documentation, https://github.com/bharatr21/mcp-nvidia#readme
Author: Bharat Raghunathan
Maintainer: Bharat Raghunathan
License: MIT
License-File: LICENSE
Keywords: ai,cuda,gpu,llm,mcp,model-context-protocol,nvidia,search
Classifier: Development Status :: 3 - Alpha
Classifier: Intended Audience :: Developers
Classifier: License :: OSI Approved :: MIT License
Classifier: Programming Language :: Python :: 3
Classifier: Programming Language :: Python :: 3.10
Classifier: Programming Language :: Python :: 3.11
Classifier: Programming Language :: Python :: 3.12
Classifier: Topic :: Internet :: WWW/HTTP :: Dynamic Content
Classifier: Topic :: Scientific/Engineering :: Artificial Intelligence
Classifier: Topic :: Software Development :: Libraries :: Python Modules
Requires-Python: >=3.10
Requires-Dist: beautifulsoup4>=4.14.0
Requires-Dist: ddgs>=9.0.0
Requires-Dist: httpx>=0.28.0
Requires-Dist: mcp>=1.1.0
Requires-Dist: nltk>=3.8.0
Requires-Dist: python-dateutil>=2.8.0
Requires-Dist: python-multipart>=0.0.9
Requires-Dist: rapidfuzz>=3.0.0
Requires-Dist: scikit-learn>=1.3.0
Requires-Dist: starlette>=0.37.0
Requires-Dist: tomli>=2.0.0; python_version < '3.11'
Requires-Dist: uvicorn>=0.30.0
Provides-Extra: dev
Requires-Dist: mypy>=1.7.0; extra == 'dev'
Requires-Dist: pre-commit>=3.5.0; extra == 'dev'
Requires-Dist: pytest-asyncio>=0.23.0; extra == 'dev'
Requires-Dist: pytest-cov>=4.1.0; extra == 'dev'
Requires-Dist: pytest>=8.0.0; extra == 'dev'
Requires-Dist: ruff>=0.8.0; extra == 'dev'
Provides-Extra: test
Requires-Dist: pytest-asyncio>=0.23.0; extra == 'test'
Requires-Dist: pytest-cov>=4.1.0; extra == 'test'
Requires-Dist: pytest>=8.0.0; extra == 'test'
Provides-Extra: ui
Requires-Dist: mcp-ui-server>=0.1.0; extra == 'ui'
